detax/__init__.py
detax/cli.py
detax-0.1.dist-info/DESCRIPTION.rst
detax-0.1.dist-info/METADATA
detax-0.1.dist-info/RECORD
detax-0.1.dist-info/WHEEL
detax-0.1.dist-info/entry_points.txt
detax-0.1.dist-info/metadata.json
detax-0.1.dist-info/top_level.txt
