Metadata-Version: 2.0
Name: detax
Version: 0.1
Summary: German income tax library
Home-page: https://github.com/mbr/detax
Author: Marc Brinkmann
Author-email: git@marcbrinkmann.de
License: MIT
Platform: UNKNOWN
Classifier: Programming Language :: Python :: 3
